{
	"credit": "Made with Blockbench",
	"parent": "thaumcraft:block/crystal_block",
	"textures": {
		"1": "thaumcraft:block/crystal_block",
		"particle": "thaumcraft:block/crystal_block"
	},
	"elements": [
		{
			"from": [8.92787, -3.45966, 5.75],
			"to": [10.42787, 1.04034, 7.25],
			"shade": false,
			"rotation": {"angle": 45, "axis": "z", "origin": [7.08953, 3, 5.3125]},
			"faces": {
				"north": {"uv": [12.5, 8.5, 13, 10.5], "texture": "#1"},
				"east": {"uv": [12, 8.5, 12.5, 10.5], "texture": "#1"},
				"south": {"uv": [13.5, 8.5, 14, 10.5], "texture": "#1"},
				"west": {"uv": [13, 8.5, 13.5, 10.5], "texture": "#1"},
				"up": {"uv": [13, 8.5, 12.5, 8], "texture": "#1"},
				"down": {"uv": [13.5, 8, 13, 8.5], "texture": "#1"}
			}
		},
		{
			"from": [12.25, -0.77936, 4.52672],
			"to": [14, 6.47064, 6.27672],
			"shade": false,
			"rotation": {"angle": -22.5, "axis": "x", "origin": [7.08953, 3, 5.3125]},
			"faces": {
				"north": {"uv": [10.5, 5.5, 11, 9], "texture": "#1"},
				"east": {"uv": [10, 5.5, 10.5, 9], "texture": "#1"},
				"south": {"uv": [11.5, 5.5, 12, 9], "texture": "#1"},
				"west": {"uv": [11, 5.5, 11.5, 9], "texture": "#1"},
				"up": {"uv": [11, 5.5, 10.5, 5], "texture": "#1"},
				"down": {"uv": [11.5, 5, 11, 5.5], "texture": "#1"}
			}
		},
		{
			"from": [12, 0, 5.75],
			"to": [14, 10, 7.75],
			"shade": false,
			"rotation": {"angle": 0, "axis": "x", "origin": [7.08953, 3, 5.3125]},
			"faces": {
				"north": {"uv": [1, 6.5, 2, 11.5], "texture": "#1"},
				"east": {"uv": [0, 6.5, 1, 11.5], "texture": "#1"},
				"south": {"uv": [3, 6.5, 4, 11.5], "texture": "#1"},
				"west": {"uv": [2, 6.5, 3, 11.5], "texture": "#1"},
				"up": {"uv": [2, 6.5, 1, 5.5], "texture": "#1"},
				"down": {"uv": [3, 5.5, 2, 6.5], "texture": "#1"}
			}
		},
		{
			"from": [1.96738, -1.23443, 2.98944],
			"to": [3.46738, 2.26557, 4.48944],
			"shade": false,
			"rotation": {"angle": 22.5, "axis": "x", "origin": [8.08953, 3, 6.3125]},
			"faces": {
				"north": {"uv": [14.5, 8.5, 15, 10], "texture": "#1"},
				"east": {"uv": [14, 8.5, 14.5, 10], "texture": "#1"},
				"south": {"uv": [15.5, 8.5, 16, 10], "texture": "#1"},
				"west": {"uv": [15, 8.5, 15.5, 10], "texture": "#1"},
				"up": {"uv": [15, 8.5, 14.5, 8], "texture": "#1"},
				"down": {"uv": [15.5, 8, 15, 8.5], "texture": "#1"}
			}
		},
		{
			"from": [1.24342, 1.73091, 0.80406],
			"to": [2.99342, 5.98091, 2.55406],
			"shade": false,
			"rotation": {"angle": 22.5, "axis": "z", "origin": [8.08953, 3, 6.3125]},
			"faces": {
				"north": {"uv": [14.5, 5.5, 15, 7.5], "texture": "#1"},
				"east": {"uv": [14, 5.5, 14.5, 7.5], "texture": "#1"},
				"south": {"uv": [15.5, 5.5, 16, 7.5], "texture": "#1"},
				"west": {"uv": [15, 5.5, 15.5, 7.5], "texture": "#1"},
				"up": {"uv": [15, 5.5, 14.5, 5], "texture": "#1"},
				"down": {"uv": [15.5, 5, 15, 5.5], "texture": "#1"}
			}
		},
		{
			"from": [1.96738, 0, 0.80406],
			"to": [3.96738, 5, 2.80406],
			"shade": false,
			"rotation": {"angle": 0, "axis": "y", "origin": [8.08953, 3, 6.3125]},
			"faces": {
				"north": {"uv": [1, 1, 2, 3.5], "texture": "#1"},
				"east": {"uv": [0, 1, 1, 3.5], "texture": "#1"},
				"south": {"uv": [3, 1, 4, 3.5], "texture": "#1"},
				"west": {"uv": [2, 1, 3, 3.5], "texture": "#1"},
				"up": {"uv": [2, 1, 1, 0], "texture": "#1"},
				"down": {"uv": [3, 0, 2, 1], "texture": "#1"}
			}
		},
		{
			"from": [0.78055, -0.61692, 6],
			"to": [1.78055, 2.38308, 7],
			"shade": false,
			"rotation": {"angle": 22.5, "axis": "z", "origin": [0.08953, 3, 11.3125]},
			"faces": {
				"north": {"uv": [10.5, 8.5, 11, 10], "texture": "#1"},
				"east": {"uv": [10, 8.5, 10.5, 10], "texture": "#1"},
				"south": {"uv": [11.5, 8.5, 12, 10], "texture": "#1"},
				"west": {"uv": [11, 8.5, 11.5, 10], "texture": "#1"},
				"up": {"uv": [11, 8.5, 10.5, 8], "texture": "#1"},
				"down": {"uv": [11.5, 8, 11, 8.5], "texture": "#1"}
			}
		},
		{
			"from": [2.1, 2.64719, 5.33036],
			"to": [3.15, 4.64719, 6.33036],
			"shade": false,
			"rotation": {"angle": -22.5, "axis": "x", "origin": [0.08953, 3, 11.3125]},
			"faces": {
				"north": {"uv": [12.5, 11, 13, 12], "texture": "#1"},
				"east": {"uv": [12, 11, 12.5, 12], "texture": "#1"},
				"south": {"uv": [13.5, 11, 14, 12], "texture": "#1"},
				"west": {"uv": [13, 11, 13.5, 12], "texture": "#1"},
				"up": {"uv": [13, 11, 12.5, 10.5], "texture": "#1"},
				"down": {"uv": [13.5, 10.5, 13, 11], "texture": "#1"}
			}
		},
		{
			"from": [2.1, -0.7096, 7.08707],
			"to": [3.15, 1.5404, 8.08707],
			"shade": false,
			"rotation": {"angle": 22.5, "axis": "x", "origin": [0.08953, 3, 11.3125]},
			"faces": {
				"north": {"uv": [14.5, 11, 15, 12], "texture": "#1"},
				"east": {"uv": [14, 11, 14.5, 12], "texture": "#1"},
				"south": {"uv": [15.5, 11, 16, 12], "texture": "#1"},
				"west": {"uv": [15, 11, 15.5, 12], "texture": "#1"},
				"up": {"uv": [15, 11, 14.5, 10.5], "texture": "#1"},
				"down": {"uv": [15.5, 10.5, 15, 11], "texture": "#1"}
			}
		},
		{
			"from": [2, 0, 6],
			"to": [3, 4, 7],
			"shade": false,
			"rotation": {"angle": 0, "axis": "x", "origin": [0.08953, 3, 11.3125]},
			"faces": {
				"north": {"uv": [8.5, 8.5, 9, 10.5], "texture": "#1"},
				"east": {"uv": [8, 8.5, 8.5, 10.5], "texture": "#1"},
				"south": {"uv": [9.5, 8.5, 10, 10.5], "texture": "#1"},
				"west": {"uv": [9, 8.5, 9.5, 10.5], "texture": "#1"},
				"up": {"uv": [9, 8.5, 8.5, 8], "texture": "#1"},
				"down": {"uv": [9.5, 8, 9, 8.5], "texture": "#1"}
			}
		},
		{
			"from": [6.75, 0, 7],
			"to": [8, 7, 8.25],
			"shade": false,
			"rotation": {"angle": 0, "axis": "y", "origin": [12.08953, 3, 2.3125]},
			"faces": {
				"north": {"uv": [8.5, 5.5, 9, 9], "texture": "#1"},
				"east": {"uv": [8, 5.5, 8.5, 9], "texture": "#1"},
				"south": {"uv": [9.5, 5.5, 10, 9], "texture": "#1"},
				"west": {"uv": [9, 5.5, 9.5, 9], "texture": "#1"},
				"up": {"uv": [9, 5.5, 8.5, 5], "texture": "#1"},
				"down": {"uv": [9.5, 5, 9, 5.5], "texture": "#1"}
			}
		},
		{
			"from": [8.22409, -1.38343, 7],
			"to": [9.47409, 2.11657, 8.25],
			"shade": false,
			"rotation": {"angle": -22.5, "axis": "z", "origin": [12.08953, 3, 2.3125]},
			"faces": {
				"north": {"uv": [14.5, 14.5, 15, 16], "texture": "#1"},
				"east": {"uv": [14, 14.5, 14.5, 16], "texture": "#1"},
				"south": {"uv": [15.5, 14.5, 16, 16], "texture": "#1"},
				"west": {"uv": [15, 14.5, 15.5, 16], "texture": "#1"},
				"up": {"uv": [15, 14.5, 14.5, 14], "texture": "#1"},
				"down": {"uv": [15.5, 14, 15, 14.5], "texture": "#1"}
			}
		},
		{
			"from": [6.75, -1.42092, 5.51845],
			"to": [7.75, 1.57908, 6.51845],
			"shade": false,
			"rotation": {"angle": -22.5, "axis": "x", "origin": [12.08953, 3, 2.3125]},
			"faces": {
				"north": {"uv": [12.5, 12.5, 13, 14], "texture": "#1"},
				"east": {"uv": [12, 12.5, 12.5, 14], "texture": "#1"},
				"south": {"uv": [13.5, 12.5, 14, 14], "texture": "#1"},
				"west": {"uv": [13, 12.5, 13.5, 14], "texture": "#1"},
				"up": {"uv": [13, 12.5, 12.5, 12], "texture": "#1"},
				"down": {"uv": [13.5, 12, 13, 12.5], "texture": "#1"}
			}
		},
		{
			"from": [6, 0.10981, 11.82293],
			"to": [7, 3.10981, 12.82293],
			"shade": false,
			"rotation": {"angle": -22.5, "axis": "x", "origin": [8.08953, 3, 12.3125]},
			"faces": {
				"north": {"uv": [14.5, 12.5, 15, 14], "texture": "#1"},
				"east": {"uv": [14, 12.5, 14.5, 14], "texture": "#1"},
				"south": {"uv": [15.5, 12.5, 16, 14], "texture": "#1"},
				"west": {"uv": [15, 12.5, 15.5, 14], "texture": "#1"},
				"up": {"uv": [15, 12.5, 14.5, 12], "texture": "#1"},
				"down": {"uv": [15.5, 12, 15, 12.5], "texture": "#1"}
			}
		},
		{
			"from": [5.91227, 0.18146, 14],
			"to": [7.01227, 3.68146, 15.05],
			"shade": false,
			"rotation": {"angle": 22.5, "axis": "x", "origin": [5.96227, 1.93146, 13.525]},
			"faces": {
				"north": {"uv": [12.5, 14.5, 13, 16], "texture": "#1"},
				"east": {"uv": [12, 14.5, 12.5, 16], "texture": "#1"},
				"south": {"uv": [13.5, 14.5, 14, 16], "texture": "#1"},
				"west": {"uv": [13, 14.5, 13.5, 16], "texture": "#1"},
				"up": {"uv": [13, 14.5, 12.5, 14], "texture": "#1"},
				"down": {"uv": [13.5, 14, 13, 14.5], "texture": "#1"}
			}
		},
		{
			"from": [6, 0, 13],
			"to": [7, 5, 14],
			"shade": false,
			"rotation": {"angle": 0, "axis": "y", "origin": [8.08953, 3, 12.3125]},
			"faces": {
				"north": {"uv": [12.5, 5.5, 13, 8], "texture": "#1"},
				"east": {"uv": [12, 5.5, 12.5, 8], "texture": "#1"},
				"south": {"uv": [13.5, 5.5, 14, 8], "texture": "#1"},
				"west": {"uv": [13, 5.5, 13.5, 8], "texture": "#1"},
				"up": {"uv": [13, 5.5, 12.5, 5], "texture": "#1"},
				"down": {"uv": [13.5, 5, 13, 5.5], "texture": "#1"}
			}
		}
	]
}